{"artifact_id":"HELIX-REBASELINE-V040-ROUTE51-DESIGN-AC18-REVIEW-V1","authority":"review-only-no-freeze-no-execution","design_ac_closure_review":{"coverage_credit":false,"denominator":18,"edge_errors":0,"executed":0,"reviewed":18,"rows":[{"closure_case_id":"DHAC-L10-001","coverage_credit":false,"errors":[],"execution_state":"designed_not_executed","primary_layer":"L10","semantic_review":"pass","source_ac_id":"AC-DH-01"},{"closure_case_id":"DHAC-L12-002","coverage_credit":false,"errors":[],"execution_state":"designed_not_executed","primary_layer":"L12","semantic_review":"pass","source_ac_id":"AC-DH-02"},{"closure_case_id":"DHAC-L10-003","coverage_credit":false,"errors":[],"execution_state":"designed_not_executed","primary_layer":"L10","semantic_review":"pass","source_ac_id":"AC-DH-03"},{"closure_case_id":"DHAC-L11-004","coverage_credit":false,"errors":[],"execution_state":"designed_not_executed","primary_layer":"L11","semantic_review":"pass","source_ac_id":"AC-DH-04"},{"closure_case_id":"DHAC-L11-005","coverage_credit":false,"errors":[],"execution_state":"designed_not_executed","primary_layer":"L11","semantic_review":"pass","source_ac_id":"AC-DH-05"},{"closure_case_id":"DHAC-L10-006","coverage_credit":false,"errors":[],"execution_state":"designed_not_executed","primary_layer":"L10","semantic_review":"pass","source_ac_id":"AC-DH-06"},{"closure_case_id":"DHAC-L10-007","coverage_credit":false,"errors":[],"execution_state":"designed_not_executed","primary_layer":"L10","semantic_review":"pass","source_ac_id":"AC-DH-07"},{"closure_case_id":"DHAC-L08-011","coverage_credit":false,"errors":[],"execution_state":"designed_not_executed","primary_layer":"L8","semantic_review":"pass","source_ac_id":"AC-DH-11"},{"closure_case_id":"DHAC-L07-012","coverage_credit":false,"errors":[],"execution_state":"designed_not_executed","primary_layer":"L7","semantic_review":"pass","source_ac_id":"AC-DH-12"},{"closure_case_id":"DHAC-L10-018","coverage_credit":false,"errors":[],"execution_state":"designed_not_executed","primary_layer":"L10","semantic_review":"pass","source_ac_id":"AC-DH-18"},{"closure_case_id":"DHAC-L08-019","coverage_credit":false,"errors":[],"execution_state":"designed_not_executed","primary_layer":"L8","semantic_review":"pass","source_ac_id":"AC-DH-19"},{"closure_case_id":"DHAC-L10-020","coverage_credit":false,"errors":[],"execution_state":"designed_not_executed","primary_layer":"L10","semantic_review":"pass","source_ac_id":"AC-DH-20"},{"closure_case_id":"DHAC-L10-021","coverage_credit":false,"errors":[],"execution_state":"designed_not_executed","primary_layer":"L10","semantic_review":"pass","source_ac_id":"AC-DH-21"},{"closure_case_id":"DHAC-L09-023","coverage_credit":false,"errors":[],"execution_state":"designed_not_executed","primary_layer":"L9","semantic_review":"pass","source_ac_id":"AC-DH-23"},{"closure_case_id":"DHAC-L07-024","coverage_credit":false,"errors":[],"execution_state":"designed_not_executed","primary_layer":"L7","semantic_review":"pass","source_ac_id":"AC-DH-24"},{"closure_case_id":"DHAC-L10-025","coverage_credit":false,"errors":[],"execution_state":"designed_not_executed","primary_layer":"L10","semantic_review":"pass","source_ac_id":"AC-DH-25"},{"closure_case_id":"DHAC-L10-026","coverage_credit":false,"errors":[],"execution_state":"designed_not_executed","primary_layer":"L10","semantic_review":"pass","source_ac_id":"AC-DH-26"},{"closure_case_id":"DHAC-L08-027","coverage_credit":false,"errors":[],"execution_state":"designed_not_executed","primary_layer":"L8","semantic_review":"pass","source_ac_id":"AC-DH-27"}],"verified":0},"input_digests":{"acceptance_criteria_sha256":"6b18bd8432cb5c33d64ec567cfc8c64b6cd94865c3be8c1d5dc5856b2184beba","design_ac_closure_sha256":"24d89b9660a2d99fd774fc168abce25a5e16f5aeb71812e3592bce0e205a3b37","requirements_catalog_sha256":"b5f85684147258e2ba3b3e34f9db3aae519142ab31a82ab8d584db438e2e2a12","route_candidate_sha256":"c67f7000d22e28dbd5b0b8e847c2df3b544162ce60628894a799f062a02cf731","traceability_sha256":"70ff370bd618fdecafa3e887bf20bd87e22802d59fc4b9b3ec63bed811490087"},"invariants":{"authority_escalation_detected":false,"candidate_is_not_verified":true,"errors":[],"execution_remains_zero":true},"route_review":{"classification_errors":0,"coverage_credit":false,"denominator":51,"disposition_counts":{"adopt":12,"defer":32,"harden":3,"redesign":4},"residual_unverified_source_edge_count":51,"reviewed":51,"rows":[{"coverage_credit":false,"disposition":"adopt","errors":[],"requirement_id":"HBR-DH-004","semantic_review":"pass","target_count":1},{"coverage_credit":false,"disposition":"adopt","errors":[],"requirement_id":"HBR-DH-005","semantic_review":"pass","target_count":1},{"coverage_credit":false,"disposition":"adopt","errors":[],"requirement_id":"HBR-DH-006","semantic_review":"pass","target_count":1},{"coverage_credit":false,"disposition":"redesign","errors":[],"requirement_id":"HBR-DH-007","semantic_review":"pass","target_count":1},{"coverage_credit":false,"disposition":"adopt","errors":[],"requirement_id":"HBR-DH-008","semantic_review":"pass","target_count":1},{"coverage_credit":false,"disposition":"adopt","errors":[],"requirement_id":"HBR-DH-009","semantic_review":"pass","target_count":1},{"coverage_credit":false,"disposition":"adopt","errors":[],"requirement_id":"HBR-DH-010","semantic_review":"pass","target_count":1},{"coverage_credit":false,"disposition":"adopt","errors":[],"requirement_id":"HBR-DH-011","semantic_review":"pass","target_count":1},{"coverage_credit":false,"disposition":"redesign","errors":[],"requirement_id":"HBR-DH-012","semantic_review":"pass","target_count":1},{"coverage_credit":false,"disposition":"harden","errors":[],"requirement_id":"HBR-DH-013","semantic_review":"pass","target_count":1},{"coverage_credit":false,"disposition":"adopt","errors":[],"requirement_id":"HBR-DH-014","semantic_review":"pass","target_count":1},{"coverage_credit":false,"disposition":"adopt","errors":[],"requirement_id":"HBR-DH-015","semantic_review":"pass","target_count":1},{"coverage_credit":false,"disposition":"adopt","errors":[],"requirement_id":"HBR-DH-016","semantic_review":"pass","target_count":1},{"coverage_credit":false,"disposition":"adopt","errors":[],"requirement_id":"HBR-DH-017","semantic_review":"pass","target_count":1},{"coverage_credit":false,"disposition":"redesign","errors":[],"requirement_id":"HBR-DH-018","semantic_review":"pass","target_count":1},{"coverage_credit":false,"disposition":"redesign","errors":[],"requirement_id":"HBR-DH-019","semantic_review":"pass","target_count":1},{"coverage_credit":false,"disposition":"harden","errors":[],"requirement_id":"HBR-DH-020","semantic_review":"pass","target_count":1},{"coverage_credit":false,"disposition":"harden","errors":[],"requirement_id":"HBR-DH-022","semantic_review":"pass","target_count":5},{"coverage_credit":false,"disposition":"adopt","errors":[],"requirement_id":"HBR-DH-023","semantic_review":"pass","target_count":3},{"coverage_credit":false,"disposition":"defer","errors":[],"requirement_id":"HBR-CORE-003","semantic_review":"pass","target_count":0},{"coverage_credit":false,"disposition":"defer","errors":[],"requirement_id":"HBR-CORE-004","semantic_review":"pass","target_count":0},{"coverage_credit":false,"disposition":"defer","errors":[],"requirement_id":"HBR-CORE-005","semantic_review":"pass","target_count":0},{"coverage_credit":false,"disposition":"defer","errors":[],"requirement_id":"HBR-CORE-006","semantic_review":"pass","target_count":0},{"coverage_credit":false,"disposition":"defer","errors":[],"requirement_id":"HBR-ARCH-003","semantic_review":"pass","target_count":0},{"coverage_credit":false,"disposition":"defer","errors":[],"requirement_id":"HBR-ARCH-004","semantic_review":"pass","target_count":0},{"coverage_credit":false,"disposition":"defer","errors":[],"requirement_id":"HBR-ARCH-006","semantic_review":"pass","target_count":0},{"coverage_credit":false,"disposition":"defer","errors":[],"requirement_id":"HBR-ARCH-007","semantic_review":"pass","target_count":0},{"coverage_credit":false,"disposition":"defer","errors":[],"requirement_id":"HBR-ARCH-011","semantic_review":"pass","target_count":0},{"coverage_credit":false,"disposition":"defer","errors":[],"requirement_id":"HBR-ARCH-012","semantic_review":"pass","target_count":0},{"coverage_credit":false,"disposition":"defer","errors":[],"requirement_id":"HNFR-PLAT-006","semantic_review":"pass","target_count":0},{"coverage_credit":false,"disposition":"defer","errors":[],"requirement_id":"HBR-ELICIT-003","semantic_review":"pass","target_count":0},{"coverage_credit":false,"disposition":"defer","errors":[],"requirement_id":"HBR-ELICIT-005","semantic_review":"pass","target_count":0},{"coverage_credit":false,"disposition":"defer","errors":[],"requirement_id":"HBR-ELICIT-006","semantic_review":"pass","target_count":0},{"coverage_credit":false,"disposition":"defer","errors":[],"requirement_id":"HBR-ELICIT-007","semantic_review":"pass","target_count":0},{"coverage_credit":false,"disposition":"defer","errors":[],"requirement_id":"HBR-ELICIT-009","semantic_review":"pass","target_count":0},{"coverage_credit":false,"disposition":"defer","errors":[],"requirement_id":"HBR-ELICIT-014","semantic_review":"pass","target_count":0},{"coverage_credit":false,"disposition":"defer","errors":[],"requirement_id":"HBR-WF-014","semantic_review":"pass","target_count":0},{"coverage_credit":false,"disposition":"defer","errors":[],"requirement_id":"HBR-DB-002","semantic_review":"pass","target_count":0},{"coverage_credit":false,"disposition":"defer","errors":[],"requirement_id":"HBR-DB-004","semantic_review":"pass","target_count":0},{"coverage_credit":false,"disposition":"defer","errors":[],"requirement_id":"HBR-DB-007","semantic_review":"pass","target_count":0},{"coverage_credit":false,"disposition":"defer","errors":[],"requirement_id":"HBR-DB-011","semantic_review":"pass","target_count":0},{"coverage_credit":false,"disposition":"defer","errors":[],"requirement_id":"HBR-DB-012","semantic_review":"pass","target_count":0},{"coverage_credit":false,"disposition":"defer","errors":[],"requirement_id":"HBR-DB-014","semantic_review":"pass","target_count":0},{"coverage_credit":false,"disposition":"defer","errors":[],"requirement_id":"HBR-INF-012","semantic_review":"pass","target_count":0},{"coverage_credit":false,"disposition":"defer","errors":[],"requirement_id":"HBR-INV-004","semantic_review":"pass","target_count":0},{"coverage_credit":false,"disposition":"defer","errors":[],"requirement_id":"HBR-INV-006","semantic_review":"pass","target_count":0},{"coverage_credit":false,"disposition":"defer","errors":[],"requirement_id":"HBR-INV-007","semantic_review":"pass","target_count":0},{"coverage_credit":false,"disposition":"defer","errors":[],"requirement_id":"HBR-INV-008","semantic_review":"pass","target_count":0},{"coverage_credit":false,"disposition":"defer","errors":[],"requirement_id":"HBR-INV-010","semantic_review":"pass","target_count":0},{"coverage_credit":false,"disposition":"defer","errors":[],"requirement_id":"HNFR-SEC-005","semantic_review":"pass","target_count":0},{"coverage_credit":false,"disposition":"defer","errors":[],"requirement_id":"HNFR-SEC-009","semantic_review":"pass","target_count":0}],"verified_source_edge_count":0},"schema_version":"helix.rebaseline.route51-design-ac18-review.v1","source_package_sha256":"c0d839bd65a221bd9614b9820cd08d3f5c21cad057bbde03bb9b2e532d05a812","status":"independent_semantic_review_pass_candidate_only"}
